mpris_fakeplayer/__init__.py
mpris_fakeplayer/installer.py
mpris_fakeplayer/logger.py
mpris_fakeplayer/media_player2_interface.py
mpris_fakeplayer/media_player2_player_interface.py
mpris_fakeplayer/mpris_fakeplayer.py
mpris_fakeplayer/resources/mpris-fakeplayer.service
mpris_fakeplayer-0.1.3.dist-info/LICENSE
mpris_fakeplayer-0.1.3.dist-info/METADATA
mpris_fakeplayer-0.1.3.dist-info/WHEEL
mpris_fakeplayer-0.1.3.dist-info/entry_points.txt
mpris_fakeplayer-0.1.3.dist-info/top_level.txt
mpris_fakeplayer-0.1.3.dist-info/RECORD
