Metadata-Version: 2.1
Name: mpris-fakeplayer
Version: 0.1.3
Summary: Fake mpris player for activating bluez avrcp volume control
Home-page: https://gitlab.com/hxss-linux/mpris-fakeplayer
Author: hxss
Author-email: hxss@ya.ru
License: MIT
Keywords: mpris,avrcp,bluez,player
Platform: UNKNOWN
Classifier: Programming Language :: Python :: 3.7
Classifier: License :: OSI Approved :: MIT License
Classifier: Operating System :: POSIX :: Linux
Classifier: Topic :: Utilities
Requires-Python: >=3.7
Requires-Dist: dbus-next (>=0.1.3)
